weather.py
weather_mcp_x-0.1.2.dist-info/METADATA
weather_mcp_x-0.1.2.dist-info/WHEEL
weather_mcp_x-0.1.2.dist-info/entry_points.txt
weather_mcp_x-0.1.2.dist-info/top_level.txt
weather_mcp_x-0.1.2.dist-info/RECORD
