Metadata-Version: 2.4
Name: weather-mcp-x
Version: 0.1.2
Summary: A weather information tool based on FastMCP framework with support for Chinese city weather alerts
Requires-Python: >=3.12
Requires-Dist: fastmcp>=2.12.4
Requires-Dist: httpx>=0.28.1
Requires-Dist: mcp[cli]>=1.18.0
